numuse/__init__.py
numuse/constants.py
numuse/converters.py
numuse/music.py
numuse/musical_system.py
numuse/notes.py
numuse/tools.py
numuse-0.1.2.dist-info/LICENSE
numuse-0.1.2.dist-info/WHEEL
numuse-0.1.2.dist-info/METADATA
numuse-0.1.2.dist-info/RECORD
