Metadata-Version: 2.1
Name: numuse
Version: 0.1.2
Summary: Music experimentation library
Home-page: https://gitlab.com/cuppajoeman/numuse
License: GPL-3.0-only
Author: ccn
Author-email: ccn@cuppajoeman.com
Requires-Python: >=3.9,<4.0
Classifier: License :: OSI Approved :: GNU General Public License v3 (GPLv3)
Classifier: Programming Language :: Python :: 3
Classifier: Programming Language :: Python :: 3.9
Project-URL: Documentation, https://numuse.readthedocs.io/en/latest/
Project-URL: Repository, https://gitlab.com/cuppajoeman/numuse
